rtl/sync_fifo.v
// =========================================================================
// Module Name:    sync_fifo
// Description:    Unified Core Synchronous FIFO Subsystem
//                 Includes: Core Array, MSB Pointer Math, Safety Fences,
//                           Real-Time Occupancy, Watermarks, and Soft Flush.
// =========================================================================

module sync_fifo (
    // Global Control Interface
    input  wire        clk,        // Core system clock (The heartbeat pulse)
    input  wire        rst_n,      // Hardware reset (0 = Reset System, 1 = Run)
    
    // Write Port (Input Channel)
    input  wire        wr_en,      // Write Enable (Set to 1 to push data in)
    input  wire [7:0]  w_data,     // 8-bit inbound data bus
    
    // Read Port (Output Channel)
    input  wire        rd_en,      // Read Enable (Set to 1 to pull data out)
    input  wire        flush,      // Synchronous Flush (1 = Instantly clear memory tracking)
    output wire [7:0]  r_data,     // 8-bit outbound data bus
    
    // Hardware Status Flags
    output wire        full,       // Status Flag: 1 means storage is 100% full
    output wire        empty,      // Status Flag: 1 means storage is 100% empty
    
    // Phase 2 Professional Ports
    output reg [3:0]   fifo_count, // Tracks the exact number of active entries (0 to 8)
    output reg         almost_full, // Early warning: FIFO is nearly full
    output reg         almost_empty // Early warning: FIFO is nearly empty
);

    // Baseline Fixed Configurations
    localparam FIFO_DEPTH = 8;     // The storage matrix has exactly 8 slots
    localparam ADDR_WIDTH = 3;     // 3 bits needed to index addresses 0 to 7 (2^3 = 8)

    // =====================================================================
    // INTERNAL STORAGE MATRIX & POINTER DECLARATIONS
    // =====================================================================
    reg [7:0] fifo_ram [0:FIFO_DEPTH-1]; // 8x8 RAM Matrix

    reg [ADDR_WIDTH:0] w_ptr; // 4-bit Write Pointer
    reg [ADDR_WIDTH:0] r_ptr; // 4-bit Read Pointer

    // =====================================================================
    // HARDWARE SAFETY PROTECTION GATES
    // =====================================================================
    wire write_allow;
    wire read_allow;

    assign write_allow = wr_en && !full && !flush;
    assign read_allow  = rd_en && !empty;

    // =====================================================================
    // MEMORY MATRIX WRITE & READ OPERATIONS
    // =====================================================================
    always @(posedge clk) begin
        if (write_allow) begin
            fifo_ram[w_ptr[ADDR_WIDTH-1:0]] <= w_data;
        end
    end

    assign r_data = fifo_ram[r_ptr[ADDR_WIDTH-1:0]];

    // =====================================================================
    // POINTER MANAGEMENT & TRACKING ENGINE (WITH FLUSH)
    // =====================================================================
    always @(posedge clk or negedge rst_n) begin
        if (!rst_n) begin
            w_ptr <= 4'b0000;
            r_ptr <= 4'b0000;
        end else if (flush) begin
            w_ptr <= 4'b0000;
            r_ptr <= 4'b0000;
        end else begin
            if (write_allow) begin
                w_ptr <= w_ptr + 1'b1;
            end
            if (read_allow) begin
                r_ptr <= r_ptr + 1'b1;
            end
        end
    end

    // =====================================================================
    // BOUNDARY FLAG STATUS GENERATION
    // =====================================================================
    assign empty = (w_ptr == r_ptr);
    
    assign full  = (w_ptr[ADDR_WIDTH] != r_ptr[ADDR_WIDTH]) && 
                   (w_ptr[ADDR_WIDTH-1:0] == r_ptr[ADDR_WIDTH-1:0]);

    // =====================================================================
    // REAL-TIME OCCUPANCY COUNTER LOGIC (WITH FLUSH)
    // =====================================================================
    always @(posedge clk or negedge rst_n) begin
        if (!rst_n) begin
            fifo_count <= 4'b0000;
        end else if (flush) begin
            fifo_count <= 4'b0000;
        end else begin
            case ({write_allow, read_allow})
                2'b10: fifo_count <= fifo_count + 1'b1;
                2'b01: fifo_count <= fifo_count - 1'b1;
                default: fifo_count <= fifo_count; // Handles 2'b00 and 2'b11 cleanly
            endcase
        end
    end

    // =====================================================================
    // WATERMARK INDICATOR LOGIC (WITH FLUSH)
    // =====================================================================
    always @(posedge clk or negedge rst_n) begin
        if (!rst_n) begin
            almost_full  <= 1'b0;
            almost_empty <= 1'b1;
        end else if (flush) begin
            almost_full  <= 1'b0;
            almost_empty <= 1'b1;
        end else begin
            almost_full  <= (fifo_count >= 4'd6);
            almost_empty <= (fifo_count <= 4'd2);
        end
    end

endmodule

tb/sync_fifo_tb.v
`timescale 1ns / 1ps

module sync_fifo_tb;

    // =====================================================================
    // 1. VIRTUAL INTERFACE WIRES (Stimulus Generators)
    // =====================================================================
    reg        clk;
    reg        rst_n;
    reg        wr_en;
    reg [7:0]  w_data;
    reg        rd_en;
    reg        flush;

    // Monitor Wires (Outputs from our Chip)
    wire [7:0] r_data;
    wire       full;
    wire       empty;
    wire [3:0] fifo_count;
    wire       almost_full;
    wire       almost_empty;

    // =====================================================================
    // 2. DEVICE UNDER TEST (DUT) INSTANTIATION
    // =====================================================================
    sync_fifo uut (
        .clk(clk),
        .rst_n(rst_n),
        .wr_en(wr_en),
        .w_data(w_data),
        .rd_en(rd_en),
        .flush(flush),
        .r_data(r_data),
        .full(full),
        .empty(empty),
        .fifo_count(fifo_count),
        .almost_full(almost_full),
        .almost_empty(almost_empty)
    );

    // =====================================================================
    // 3. CLOCK GENERATOR ENGINE (50 MHz Heartbeat)
    // =====================================================================
    always begin
        #10 clk = ~clk; // Toggle clock every 10ns (20ns total cycle period)
    end

    // =====================================================================
    // 4. AUTOMATED SIMULATION TEST VECTOR SUITE
    // =====================================================================
    initial begin
        // Setup GTKWave Waveform Dumping
        $dumpfile("sync_fifo_sim.vcd"); 
        $dumpvars(0, sync_fifo_tb);     
        
        // --- TEST 1: SYSTEM INITIALIZATION & RESET ---
        clk   = 1'b0;
        rst_n = 1'b0; 
        wr_en = 1'b0;
        w_data = 8'h00;
        rd_en = 1'b0;
        flush = 1'b0;
        #40;          
        
        rst_n = 1'b1; // Release hardware reset
        #20;
        
        // --- TEST 2: BURST WRITE OPERATIONS (Fill up the FIFO) ---
        $display("[INFO] Starting Write Burst Operations...");
        write_byte(8'd10);
        write_byte(8'd20);
        write_byte(8'd30);
        write_byte(8'd40);
        write_byte(8'd50); // Count reaches 5: almost_full triggers high!
        write_byte(8'd60);
        write_byte(8'd70);
        write_byte(8'd80); // Count reaches 8: full triggers high!
        #20;
        
        // --- TEST 3: ATTEMPT AN ILLEGAL OVERFLOW WRITE ---
        write_byte(8'd99); // Blocked completely by hardware safety gates
        #20;

        // --- TEST 4: BURST READ OPERATIONS (Empty out the FIFO) ---
        $display("[INFO] Starting Read Burst Operations...");
        read_byte();
        read_byte();
        read_byte();
        read_byte();
        read_byte();
        read_byte();
        read_byte();
        read_byte(); // FIFO drops to empty!
        #20;

        // --- TEST 5: TEST SYNCHRONOUS FLUSH FEATURE ---
        $display("[INFO] Testing Synchronous Flush Operations...");
        write_byte(8'hAA); 
        write_byte(8'hBB);
        #20;
        
        flush = 1'b1;      // Activate soft flush
        #20;
        flush = 1'b0;      // Release soft flush
        #40;

        $display("[SUCCESS] All FIFO Subsystem tests passed cleanly!");
        $finish;
    end

    // =====================================================================
    // 5. REUSABLE HARDWARE SIMULATION TASKS
    // =====================================================================
    task write_byte(input [7:0] data_in);
        begin
            @(posedge clk);
            #1;
            wr_en  = 1'b1;
            w_data = data_in;
            @(posedge clk);
            #1;
            wr_en  = 1'b0;
        end
    endtask

    task read_byte();
        begin
            @(posedge clk);
            #1;
            rd_en = 1'b1;
            @(posedge clk);
            #1;
            rd_en = 1'b0;
        end
    endtask

endmodule

sync_fifo_sim.vcd
$date
	Mon Jun 01 15:54:30 2026
$end
$version
	Icarus Verilog
$end
$timescale
	1ps
$end
$scope module sync_fifo_tb $end
$var wire 8 ! r_data [7:0] $end
$var wire 1 " full $end
$var wire 4 # fifo_count [3:0] $end
$var wire 1 $ empty $end
$var wire 1 % almost_full $end
$var wire 1 & almost_empty $end
$var reg 1 ' clk $end
$var reg 1 ( flush $end
$var reg 1 ) rd_en $end
$var reg 1 * rst_n $end
$var reg 8 + w_data [7:0] $end
$var reg 1 , wr_en $end
$scope module uut $end
$var wire 1 ' clk $end
$var wire 1 ( flush $end
$var wire 1 " full $end
$var wire 8 - r_data [7:0] $end
$var wire 1 ) rd_en $end
$var wire 1 . read_allow $end
$var wire 1 * rst_n $end
$var wire 8 / w_data [7:0] $end
$var wire 1 , wr_en $end
$var wire 1 0 write_allow $end
$var wire 1 $ empty $end
$var parameter 32 1 ADDR_WIDTH $end
$var parameter 32 2 FIFO_DEPTH $end
$var reg 1 & almost_empty $end
$var reg 1 % almost_full $end
$var reg 4 3 fifo_count [3:0] $end
$var reg 4 4 r_ptr [3:0] $end
$var reg 4 5 w_ptr [3:0] $end
$upscope $end
$scope task read_byte $end
$upscope $end
$scope task write_byte $end
$var reg 8 6 data_in [7:0] $end
$upscope $end
$upscope $end
$enddefinitions $end
$comment Show the parameter values. $end
$dumpall
b1000 2
b11 1
$end
#0
$dumpvars
bx 6
b0 5
b0 4
b0 3
00
b0 /
0.
bx -
0,
b0 +
0*
0)
0(
0'
1&
0%
1$
b0 #
0"
bx !
$end
#10000
1'
#20000
0'
#30000
1'
#40000
0'
1*
#50000
1'
#60000
0'
b1010 6
#70000
1'
#71000
10
b1010 +
b1010 /
1,
#80000
0'
#90000
b1 #
b1 3
0$
b1 5
b1010 !
b1010 -
1'
#91000
00
b10100 6
0,
#100000
0'
#110000
1'
#111000
10
b10100 +
b10100 /
1,
#120000
0'
#130000
b10 #
b10 3
b10 5
1'
#131000
00
b11110 6
0,
#140000
0'
#150000
1'
#151000
10
b11110 +
b11110 /
1,
#160000
0'
#170000
b11 #
b11 3
b11 5
1'
#171000
00
b101000 6
0,
#180000
0'
#190000
0&
1'
#191000
10
b101000 +
b101000 /
1,
#200000
0'
#210000
b100 #
b100 3
b100 5
1'
#211000
00
b110010 6
0,
#220000
0'
#230000
1'
#231000
10
b110010 +
b110010 /
1,
#240000
0'
#250000
b101 #
b101 3
b101 5
1'
#251000
00
b111100 6
0,
#260000
0'
#270000
1'
#271000
10
b111100 +
b111100 /
1,
#280000
0'
#290000
b110 #
b110 3
b110 5
1'
#291000
00
b1000110 6
0,
#300000
0'
#310000
1%
1'
#311000
10
b1000110 +
b1000110 /
1,
#320000
0'
#330000
b111 #
b111 3
b111 5
1'
#331000
00
b1010000 6
0,
#340000
0'
#350000
1'
#351000
10
b1010000 +
b1010000 /
1,
#360000
0'
#370000
00
1"
b1000 #
b1000 3
b1000 5
1'
#371000
0,
#380000
0'
#390000
1'
#391000
b1100011 6
#400000
0'
#410000
1'
#411000
b1100011 +
b1100011 /
1,
#420000
0'
#430000
1'
#431000
0,
#440000
0'
#450000
1'
#460000
0'
#470000
1'
#471000
1.
1)
#480000
0'
#490000
0"
b10100 !
b10100 -
b111 #
b111 3
b1 4
1'
#491000
0.
0)
#500000
0'
#510000
1'
#511000
1.
1)
#520000
0'
#530000
b11110 !
b11110 -
b110 #
b110 3
b10 4
1'
#531000
0.
0)
#540000
0'
#550000
1'
#551000
1.
1)
#560000
0'
#570000
b101000 !
b101000 -
b101 #
b101 3
b11 4
1'
#571000
0.
0)
#580000
0'
#590000
0%
1'
#591000
1.
1)
#600000
0'
#610000
b110010 !
b110010 -
b100 #
b100 3
b100 4
1'
#611000
0.
0)
#620000
0'
#630000
1'
#631000
1.
1)
#640000
0'
#650000
b111100 !
b111100 -
b11 #
b11 3
b101 4
1'
#651000
0.
0)
#660000
0'
#670000
1'
#671000
1.
1)
#680000
0'
#690000
b1000110 !
b1000110 -
b10 #
b10 3
b110 4
1'
#691000
0.
0)
#700000
0'
#710000
1&
1'
#711000
1.
1)
#720000
0'
#730000
b1010000 !
b1010000 -
b1 #
b1 3
b111 4
1'
#731000
0.
0)
#740000
0'
#750000
1'
#751000
1.
1)
#760000
0'
#770000
0"
b1010 !
b1010 -
0.
b0 #
b0 3
1$
b1000 4
1'
#771000
0)
#780000
0'
#790000
1'
#791000
b10101010 6
#800000
0'
#810000
1'
#811000
10
b10101010 +
b10101010 /
1,
#820000
0'
#830000
0$
b1001 5
b1 #
b1 3
b10101010 !
b10101010 -
1'
#831000
00
b10111011 6
0,
#840000
0'
#850000
1'
#851000
10
b10111011 +
b10111011 /
1,
#860000
0'
#870000
b1010 5
b10 #
b10 3
1'
#871000
00
0,
#880000
0'
#890000
1'
#891000
1(
#900000
0'
#910000
1$
b0 4
b0 5
b0 #
b0 3
1'
#911000
0(
